gsimporter/__init__.py
gsimporter/_util.py
gsimporter/api.py
gsimporter/client.py
test/__init__.py
test/uploadtests.py
gn_gsimporter-2.0.3.dist-info/METADATA
gn_gsimporter-2.0.3.dist-info/WHEEL
gn_gsimporter-2.0.3.dist-info/top_level.txt
gn_gsimporter-2.0.3.dist-info/RECORD
